{
  "csgi_version": "1.0",
  "letter": "I",
  "name": "uppercase_I",
  "adjacency": "8-neighborhood",
  "release": "CSGI-LATIN-v1.0",
  "stats": {
    "node_count": 15,
    "edge_count": 21
  },
  "nodes": [
    {
      "id": 0,
      "x": 235,
      "y": 162,
      "degree": 1
    },
    {
      "id": 1,
      "x": 292,
      "y": 162,
      "degree": 3
    },
    {
      "id": 2,
      "x": 293,
      "y": 162,
      "degree": 3
    },
    {
      "id": 3,
      "x": 347,
      "y": 162,
      "degree": 1
    },
    {
      "id": 4,
      "x": 290,
      "y": 163,
      "degree": 3
    },
    {
      "id": 5,
      "x": 291,
      "y": 163,
      "degree": 4
    },
    {
      "id": 6,
      "x": 292,
      "y": 163,
      "degree": 4
    },
    {
      "id": 7,
      "x": 291,
      "y": 164,
      "degree": 4
    },
    {
      "id": 8,
      "x": 291,
      "y": 378,
      "degree": 3
    },
    {
      "id": 9,
      "x": 290,
      "y": 379,
      "degree": 4
    },
    {
      "id": 10,
      "x": 291,
      "y": 379,
      "degree": 4
    },
    {
      "id": 11,
      "x": 289,
      "y": 380,
      "degree": 3
    },
    {
      "id": 12,
      "x": 290,
      "y": 380,
      "degree": 3
    },
    {
      "id": 13,
      "x": 235,
      "y": 381,
      "degree": 1
    },
    {
      "id": 14,
      "x": 347,
      "y": 381,
      "degree": 1
    }
  ],
  "edges": [
    {
      "id": 0,
      "u": 0,
      "v": 4,
      "points": [
        [
          235,
          162
        ],
        [
          236,
          162
        ],
        [
          237,
          162
        ],
        [
          238,
          162
        ],
        [
          239,
          162
        ],
        [
          240,
          162
        ],
        [
          241,
          162
        ],
        [
          242,
          162
        ],
        [
          243,
          162
        ],
        [
          244,
          162
        ],
        [
          245,
          162
        ],
        [
          246,
          162
        ],
        [
          247,
          162
        ],
        [
          248,
          162
        ],
        [
          249,
          162
        ],
        [
          250,
          162
        ],
        [
          251,
          162
        ],
        [
          252,
          162
        ],
        [
          253,
          162
        ],
        [
          254,
          162
        ],
        [
          255,
          162
        ],
        [
          256,
          162
        ],
        [
          257,
          162
        ],
        [
          258,
          162
        ],
        [
          259,
          162
        ],
        [
          260,
          162
        ],
        [
          261,
          162
        ],
        [
          262,
          162
        ],
        [
          263,
          162
        ],
        [
          264,
          162
        ],
        [
          265,
          162
        ],
        [
          266,
          162
        ],
        [
          267,
          162
        ],
        [
          268,
          162
        ],
        [
          269,
          162
        ],
        [
          270,
          162
        ],
        [
          271,
          162
        ],
        [
          272,
          162
        ],
        [
          273,
          162
        ],
        [
          274,
          162
        ],
        [
          275,
          162
        ],
        [
          276,
          162
        ],
        [
          277,
          162
        ],
        [
          278,
          162
        ],
        [
          279,
          162
        ],
        [
          280,
          162
        ],
        [
          281,
          162
        ],
        [
          282,
          162
        ],
        [
          283,
          162
        ],
        [
          284,
          162
        ],
        [
          285,
          162
        ],
        [
          286,
          162
        ],
        [
          287,
          162
        ],
        [
          288,
          162
        ],
        [
          289,
          162
        ],
        [
          290,
          163
        ]
      ]
    },
    {
      "id": 1,
      "u": 1,
      "v": 2,
      "points": [
        [
          292,
          162
        ],
        [
          293,
          162
        ]
      ]
    },
    {
      "id": 2,
      "u": 1,
      "v": 5,
      "points": [
        [
          292,
          162
        ],
        [
          291,
          163
        ]
      ]
    },
    {
      "id": 3,
      "u": 1,
      "v": 6,
      "points": [
        [
          292,
          162
        ],
        [
          292,
          163
        ]
      ]
    },
    {
      "id": 4,
      "u": 2,
      "v": 3,
      "points": [
        [
          293,
          162
        ],
        [
          294,
          162
        ],
        [
          295,
          162
        ],
        [
          296,
          162
        ],
        [
          297,
          162
        ],
        [
          298,
          162
        ],
        [
          299,
          162
        ],
        [
          300,
          162
        ],
        [
          301,
          162
        ],
        [
          302,
          162
        ],
        [
          303,
          162
        ],
        [
          304,
          162
        ],
        [
          305,
          162
        ],
        [
          306,
          162
        ],
        [
          307,
          162
        ],
        [
          308,
          162
        ],
        [
          309,
          162
        ],
        [
          310,
          162
        ],
        [
          311,
          162
        ],
        [
          312,
          162
        ],
        [
          313,
          162
        ],
        [
          314,
          162
        ],
        [
          315,
          162
        ],
        [
          316,
          162
        ],
        [
          317,
          162
        ],
        [
          318,
          162
        ],
        [
          319,
          162
        ],
        [
          320,
          162
        ],
        [
          321,
          162
        ],
        [
          322,
          162
        ],
        [
          323,
          162
        ],
        [
          324,
          162
        ],
        [
          325,
          162
        ],
        [
          326,
          162
        ],
        [
          327,
          162
        ],
        [
          328,
          162
        ],
        [
          329,
          162
        ],
        [
          330,
          162
        ],
        [
          331,
          162
        ],
        [
          332,
          162
        ],
        [
          333,
          162
        ],
        [
          334,
          162
        ],
        [
          335,
          162
        ],
        [
          336,
          162
        ],
        [
          337,
          162
        ],
        [
          338,
          162
        ],
        [
          339,
          162
        ],
        [
          340,
          162
        ],
        [
          341,
          162
        ],
        [
          342,
          162
        ],
        [
          343,
          162
        ],
        [
          344,
          162
        ],
        [
          345,
          162
        ],
        [
          346,
          162
        ],
        [
          347,
          162
        ]
      ]
    },
    {
      "id": 5,
      "u": 2,
      "v": 6,
      "points": [
        [
          293,
          162
        ],
        [
          292,
          163
        ]
      ]
    },
    {
      "id": 6,
      "u": 4,
      "v": 5,
      "points": [
        [
          290,
          163
        ],
        [
          291,
          163
        ]
      ]
    },
    {
      "id": 7,
      "u": 4,
      "v": 7,
      "points": [
        [
          290,
          163
        ],
        [
          291,
          164
        ]
      ]
    },
    {
      "id": 8,
      "u": 5,
      "v": 6,
      "points": [
        [
          291,
          163
        ],
        [
          292,
          163
        ]
      ]
    },
    {
      "id": 9,
      "u": 5,
      "v": 7,
      "points": [
        [
          291,
          163
        ],
        [
          291,
          164
        ]
      ]
    },
    {
      "id": 10,
      "u": 6,
      "v": 7,
      "points": [
        [
          292,
          163
        ],
        [
          291,
          164
        ]
      ]
    },
    {
      "id": 11,
      "u": 7,
      "v": 8,
      "points": [
        [
          291,
          164
        ],
        [
          291,
          165
        ],
        [
          291,
          166
        ],
        [
          291,
          167
        ],
        [
          291,
          168
        ],
        [
          291,
          169
        ],
        [
          291,
          170
        ],
        [
          291,
          171
        ],
        [
          291,
          172
        ],
        [
          291,
          173
        ],
        [
          291,
          174
        ],
        [
          291,
          175
        ],
        [
          291,
          176
        ],
        [
          291,
          177
        ],
        [
          291,
          178
        ],
        [
          291,
          179
        ],
        [
          291,
          180
        ],
        [
          291,
          181
        ],
        [
          291,
          182
        ],
        [
          291,
          183
        ],
        [
          291,
          184
        ],
        [
          291,
          185
        ],
        [
          291,
          186
        ],
        [
          291,
          187
        ],
        [
          291,
          188
        ],
        [
          291,
          189
        ],
        [
          291,
          190
        ],
        [
          291,
          191
        ],
        [
          291,
          192
        ],
        [
          291,
          193
        ],
        [
          291,
          194
        ],
        [
          291,
          195
        ],
        [
          291,
          196
        ],
        [
          291,
          197
        ],
        [
          291,
          198
        ],
        [
          291,
          199
        ],
        [
          291,
          200
        ],
        [
          291,
          201
        ],
        [
          291,
          202
        ],
        [
          291,
          203
        ],
        [
          291,
          204
        ],
        [
          291,
          205
        ],
        [
          291,
          206
        ],
        [
          291,
          207
        ],
        [
          291,
          208
        ],
        [
          291,
          209
        ],
        [
          291,
          210
        ],
        [
          291,
          211
        ],
        [
          291,
          212
        ],
        [
          291,
          213
        ],
        [
          291,
          214
        ],
        [
          291,
          215
        ],
        [
          291,
          216
        ],
        [
          291,
          217
        ],
        [
          291,
          218
        ],
        [
          291,
          219
        ],
        [
          291,
          220
        ],
        [
          291,
          221
        ],
        [
          291,
          222
        ],
        [
          291,
          223
        ],
        [
          291,
          224
        ],
        [
          291,
          225
        ],
        [
          291,
          226
        ],
        [
          291,
          227
        ],
        [
          291,
          228
        ],
        [
          291,
          229
        ],
        [
          291,
          230
        ],
        [
          291,
          231
        ],
        [
          291,
          232
        ],
        [
          291,
          233
        ],
        [
          291,
          234
        ],
        [
          291,
          235
        ],
        [
          291,
          236
        ],
        [
          291,
          237
        ],
        [
          291,
          238
        ],
        [
          291,
          239
        ],
        [
          291,
          240
        ],
        [
          291,
          241
        ],
        [
          291,
          242
        ],
        [
          291,
          243
        ],
        [
          291,
          244
        ],
        [
          291,
          245
        ],
        [
          291,
          246
        ],
        [
          291,
          247
        ],
        [
          291,
          248
        ],
        [
          291,
          249
        ],
        [
          291,
          250
        ],
        [
          291,
          251
        ],
        [
          291,
          252
        ],
        [
          291,
          253
        ],
        [
          291,
          254
        ],
        [
          291,
          255
        ],
        [
          291,
          256
        ],
        [
          291,
          257
        ],
        [
          291,
          258
        ],
        [
          291,
          259
        ],
        [
          291,
          260
        ],
        [
          291,
          261
        ],
        [
          291,
          262
        ],
        [
          291,
          263
        ],
        [
          291,
          264
        ],
        [
          291,
          265
        ],
        [
          291,
          266
        ],
        [
          291,
          267
        ],
        [
          291,
          268
        ],
        [
          291,
          269
        ],
        [
          291,
          270
        ],
        [
          291,
          271
        ],
        [
          291,
          272
        ],
        [
          291,
          273
        ],
        [
          291,
          274
        ],
        [
          291,
          275
        ],
        [
          291,
          276
        ],
        [
          291,
          277
        ],
        [
          291,
          278
        ],
        [
          291,
          279
        ],
        [
          291,
          280
        ],
        [
          291,
          281
        ],
        [
          291,
          282
        ],
        [
          291,
          283
        ],
        [
          291,
          284
        ],
        [
          291,
          285
        ],
        [
          291,
          286
        ],
        [
          291,
          287
        ],
        [
          291,
          288
        ],
        [
          291,
          289
        ],
        [
          291,
          290
        ],
        [
          291,
          291
        ],
        [
          291,
          292
        ],
        [
          291,
          293
        ],
        [
          291,
          294
        ],
        [
          291,
          295
        ],
        [
          291,
          296
        ],
        [
          291,
          297
        ],
        [
          291,
          298
        ],
        [
          291,
          299
        ],
        [
          291,
          300
        ],
        [
          291,
          301
        ],
        [
          291,
          302
        ],
        [
          291,
          303
        ],
        [
          291,
          304
        ],
        [
          291,
          305
        ],
        [
          291,
          306
        ],
        [
          291,
          307
        ],
        [
          291,
          308
        ],
        [
          291,
          309
        ],
        [
          291,
          310
        ],
        [
          291,
          311
        ],
        [
          291,
          312
        ],
        [
          291,
          313
        ],
        [
          291,
          314
        ],
        [
          291,
          315
        ],
        [
          291,
          316
        ],
        [
          291,
          317
        ],
        [
          291,
          318
        ],
        [
          291,
          319
        ],
        [
          291,
          320
        ],
        [
          291,
          321
        ],
        [
          291,
          322
        ],
        [
          291,
          323
        ],
        [
          291,
          324
        ],
        [
          291,
          325
        ],
        [
          291,
          326
        ],
        [
          291,
          327
        ],
        [
          291,
          328
        ],
        [
          291,
          329
        ],
        [
          291,
          330
        ],
        [
          291,
          331
        ],
        [
          291,
          332
        ],
        [
          291,
          333
        ],
        [
          291,
          334
        ],
        [
          291,
          335
        ],
        [
          291,
          336
        ],
        [
          291,
          337
        ],
        [
          291,
          338
        ],
        [
          291,
          339
        ],
        [
          291,
          340
        ],
        [
          291,
          341
        ],
        [
          291,
          342
        ],
        [
          291,
          343
        ],
        [
          291,
          344
        ],
        [
          291,
          345
        ],
        [
          291,
          346
        ],
        [
          291,
          347
        ],
        [
          291,
          348
        ],
        [
          291,
          349
        ],
        [
          291,
          350
        ],
        [
          291,
          351
        ],
        [
          291,
          352
        ],
        [
          291,
          353
        ],
        [
          291,
          354
        ],
        [
          291,
          355
        ],
        [
          291,
          356
        ],
        [
          291,
          357
        ],
        [
          291,
          358
        ],
        [
          291,
          359
        ],
        [
          291,
          360
        ],
        [
          291,
          361
        ],
        [
          291,
          362
        ],
        [
          291,
          363
        ],
        [
          291,
          364
        ],
        [
          291,
          365
        ],
        [
          291,
          366
        ],
        [
          291,
          367
        ],
        [
          291,
          368
        ],
        [
          291,
          369
        ],
        [
          291,
          370
        ],
        [
          291,
          371
        ],
        [
          291,
          372
        ],
        [
          291,
          373
        ],
        [
          291,
          374
        ],
        [
          291,
          375
        ],
        [
          291,
          376
        ],
        [
          291,
          377
        ],
        [
          291,
          378
        ]
      ]
    },
    {
      "id": 12,
      "u": 8,
      "v": 9,
      "points": [
        [
          291,
          378
        ],
        [
          290,
          379
        ]
      ]
    },
    {
      "id": 13,
      "u": 8,
      "v": 10,
      "points": [
        [
          291,
          378
        ],
        [
          291,
          379
        ]
      ]
    },
    {
      "id": 14,
      "u": 9,
      "v": 10,
      "points": [
        [
          290,
          379
        ],
        [
          291,
          379
        ]
      ]
    },
    {
      "id": 15,
      "u": 9,
      "v": 11,
      "points": [
        [
          290,
          379
        ],
        [
          289,
          380
        ]
      ]
    },
    {
      "id": 16,
      "u": 9,
      "v": 12,
      "points": [
        [
          290,
          379
        ],
        [
          290,
          380
        ]
      ]
    },
    {
      "id": 17,
      "u": 10,
      "v": 12,
      "points": [
        [
          291,
          379
        ],
        [
          290,
          380
        ]
      ]
    },
    {
      "id": 18,
      "u": 10,
      "v": 14,
      "points": [
        [
          291,
          379
        ],
        [
          292,
          380
        ],
        [
          293,
          381
        ],
        [
          294,
          381
        ],
        [
          295,
          381
        ],
        [
          296,
          381
        ],
        [
          297,
          381
        ],
        [
          298,
          381
        ],
        [
          299,
          381
        ],
        [
          300,
          381
        ],
        [
          301,
          381
        ],
        [
          302,
          381
        ],
        [
          303,
          381
        ],
        [
          304,
          381
        ],
        [
          305,
          381
        ],
        [
          306,
          381
        ],
        [
          307,
          381
        ],
        [
          308,
          381
        ],
        [
          309,
          381
        ],
        [
          310,
          381
        ],
        [
          311,
          381
        ],
        [
          312,
          381
        ],
        [
          313,
          381
        ],
        [
          314,
          381
        ],
        [
          315,
          381
        ],
        [
          316,
          381
        ],
        [
          317,
          381
        ],
        [
          318,
          381
        ],
        [
          319,
          381
        ],
        [
          320,
          381
        ],
        [
          321,
          381
        ],
        [
          322,
          381
        ],
        [
          323,
          381
        ],
        [
          324,
          381
        ],
        [
          325,
          381
        ],
        [
          326,
          381
        ],
        [
          327,
          381
        ],
        [
          328,
          381
        ],
        [
          329,
          381
        ],
        [
          330,
          381
        ],
        [
          331,
          381
        ],
        [
          332,
          381
        ],
        [
          333,
          381
        ],
        [
          334,
          381
        ],
        [
          335,
          381
        ],
        [
          336,
          381
        ],
        [
          337,
          381
        ],
        [
          338,
          381
        ],
        [
          339,
          381
        ],
        [
          340,
          381
        ],
        [
          341,
          381
        ],
        [
          342,
          381
        ],
        [
          343,
          381
        ],
        [
          344,
          381
        ],
        [
          345,
          381
        ],
        [
          346,
          381
        ],
        [
          347,
          381
        ]
      ]
    },
    {
      "id": 19,
      "u": 11,
      "v": 12,
      "points": [
        [
          289,
          380
        ],
        [
          290,
          380
        ]
      ]
    },
    {
      "id": 20,
      "u": 11,
      "v": 13,
      "points": [
        [
          289,
          380
        ],
        [
          288,
          381
        ],
        [
          287,
          381
        ],
        [
          286,
          381
        ],
        [
          285,
          381
        ],
        [
          284,
          381
        ],
        [
          283,
          381
        ],
        [
          282,
          381
        ],
        [
          281,
          381
        ],
        [
          280,
          381
        ],
        [
          279,
          381
        ],
        [
          278,
          381
        ],
        [
          277,
          381
        ],
        [
          276,
          381
        ],
        [
          275,
          381
        ],
        [
          274,
          381
        ],
        [
          273,
          381
        ],
        [
          272,
          381
        ],
        [
          271,
          381
        ],
        [
          270,
          381
        ],
        [
          269,
          381
        ],
        [
          268,
          381
        ],
        [
          267,
          381
        ],
        [
          266,
          381
        ],
        [
          265,
          381
        ],
        [
          264,
          381
        ],
        [
          263,
          381
        ],
        [
          262,
          381
        ],
        [
          261,
          381
        ],
        [
          260,
          381
        ],
        [
          259,
          381
        ],
        [
          258,
          381
        ],
        [
          257,
          381
        ],
        [
          256,
          381
        ],
        [
          255,
          381
        ],
        [
          254,
          381
        ],
        [
          253,
          381
        ],
        [
          252,
          381
        ],
        [
          251,
          381
        ],
        [
          250,
          381
        ],
        [
          249,
          381
        ],
        [
          248,
          381
        ],
        [
          247,
          381
        ],
        [
          246,
          381
        ],
        [
          245,
          381
        ],
        [
          244,
          381
        ],
        [
          243,
          381
        ],
        [
          242,
          381
        ],
        [
          241,
          381
        ],
        [
          240,
          381
        ],
        [
          239,
          381
        ],
        [
          238,
          381
        ],
        [
          237,
          381
        ],
        [
          236,
          381
        ],
        [
          235,
          381
        ]
      ]
    }
  ]
}